{
    "name": "Puesto",
    "fields": [
        {
            "fieldName": "nombre",
            "fieldType": "String",
            "fieldValidateRules": [
                "required"
            ]
        },
        {
            "fieldName": "horario",
            "fieldType": "String"
        },
        {
            "fieldName": "salario",
            "fieldType": "Double"
        }
    ],
    "relationships": [],
    "changelogDate": "20221205144014",
    "entityTableName": "puesto",
    "dto": "mapstruct",
    "pagination": "pagination",
    "service": "serviceImpl",
    "jpaMetamodelFiltering": false,
    "fluentMethods": true,
    "clientRootFolder": "",
    "applications": "*"
}